undate/__init__.py
undate/date.py
undate/interval.py
undate/undate.py
undate/converters/__init__.py
undate/converters/base.py
undate/converters/combined.py
undate/converters/iso8601.py
undate/converters/calendars/__init__.py
undate/converters/calendars/gregorian.py
undate/converters/calendars/seleucid.py
undate/converters/calendars/hebrew/__init__.py
undate/converters/calendars/hebrew/converter.py
undate/converters/calendars/hebrew/parser.py
undate/converters/calendars/hebrew/transformer.py
undate/converters/calendars/islamic/__init__.py
undate/converters/calendars/islamic/converter.py
undate/converters/calendars/islamic/parser.py
undate/converters/calendars/islamic/transformer.py
undate/converters/edtf/__init__.py
undate/converters/edtf/converter.py
undate/converters/edtf/parser.py
undate/converters/edtf/transformer.py
undate/converters/grammars/combined.lark
undate/converters/grammars/edtf.lark
undate/converters/grammars/hebrew.lark
undate/converters/grammars/islamic.lark
undate-0.6.0.dist-info/METADATA
undate-0.6.0.dist-info/WHEEL
undate-0.6.0.dist-info/licenses/LICENSE.md
undate-0.6.0.dist-info/RECORD
