Metadata-Version: 2.4
Name: undate
Version: 0.6.0
Summary: library for working with uncertain, fuzzy, or partially unknown dates and date intervals
Project-URL: Homepage, https://github.com/dh-tech/undate-python
Project-URL: Documentation, https://undate-python.readthedocs.io/en/latest/
Project-URL: Repository, https://github.com/dh-tech/undate-python.git
Project-URL: Issues, https://github.com/dh-tech/undate-python/issues
Project-URL: Changelog, https://github.com/dh-tech/undate-python/blob/main/CHANGELOG.md
Author: Rebecca Sutton Koeser, Cole Crawford, Julia Damerow, Robert Casties, Malte Vogl
License: Apache-2
License-File: LICENSE.md
Keywords: dates,dating,digital-humanities,partially-known,uncertain-dates,uncertainty,unknown
Classifier: Development Status :: 4 - Beta
Classifier: Intended Audience :: Developers
Classifier: Intended Audience :: Science/Research
Classifier: License :: OSI Approved :: Apache Software License
Classifier: Operating System :: OS Independent
Classifier: Programming Language :: Python :: 3
Classifier: Programming Language :: Python :: 3.10
Classifier: Programming Language :: Python :: 3.11
Classifier: Programming Language :: Python :: 3.12
Classifier: Programming Language :: Python :: 3.13
Classifier: Topic :: Scientific/Engineering
Classifier: Topic :: Software Development :: Libraries :: Python Modules
Classifier: Topic :: Utilities
Classifier: Typing :: Typed
Requires-Python: >=3.10
Requires-Dist: convertdate
Requires-Dist: lark[interegular]
Requires-Dist: numpy
Requires-Dist: strenum; python_version < '3.11'
Provides-Extra: all
Requires-Dist: alabaster; extra == 'all'
Requires-Dist: altair; extra == 'all'
Requires-Dist: build; extra == 'all'
Requires-Dist: jupyterlab; extra == 'all'
Requires-Dist: mypy; extra == 'all'
Requires-Dist: myst-parser; extra == 'all'
Requires-Dist: myst-parser[linkify]; extra == 'all'
Requires-Dist: pandas; extra == 'all'
Requires-Dist: pre-commit>=2.20.0; extra == 'all'
Requires-Dist: pytest-cov; extra == 'all'
Requires-Dist: pytest-ordering; extra == 'all'
Requires-Dist: pytest>=7.2; extra == 'all'
Requires-Dist: ruff; extra == 'all'
Requires-Dist: sphinx>=7.0.0; extra == 'all'
Requires-Dist: treon; extra == 'all'
Requires-Dist: twine; extra == 'all'
Requires-Dist: wheel; extra == 'all'
Provides-Extra: check
Requires-Dist: alabaster; extra == 'check'
Requires-Dist: altair; extra == 'check'
Requires-Dist: jupyterlab; extra == 'check'
Requires-Dist: mypy; extra == 'check'
Requires-Dist: myst-parser; extra == 'check'
Requires-Dist: myst-parser[linkify]; extra == 'check'
Requires-Dist: pandas; extra == 'check'
Requires-Dist: ruff; extra == 'check'
Requires-Dist: sphinx>=7.0.0; extra == 'check'
Requires-Dist: treon; extra == 'check'
Provides-Extra: dev
Requires-Dist: alabaster; extra == 'dev'
Requires-Dist: altair; extra == 'dev'
Requires-Dist: build; extra == 'dev'
Requires-Dist: jupyterlab; extra == 'dev'
Requires-Dist: mypy; extra == 'dev'
Requires-Dist: myst-parser; extra == 'dev'
Requires-Dist: myst-parser[linkify]; extra == 'dev'
Requires-Dist: pandas; extra == 'dev'
Requires-Dist: pre-commit>=2.20.0; extra == 'dev'
Requires-Dist: pytest-cov; extra == 'dev'
Requires-Dist: pytest-ordering; extra == 'dev'
Requires-Dist: pytest>=7.2; extra == 'dev'
Requires-Dist: ruff; extra == 'dev'
Requires-Dist: sphinx>=7.0.0; extra == 'dev'
Requires-Dist: treon; extra == 'dev'
Requires-Dist: twine; extra == 'dev'
Requires-Dist: wheel; extra == 'dev'
Provides-Extra: docs
Requires-Dist: alabaster; extra == 'docs'
Requires-Dist: myst-parser; extra == 'docs'
Requires-Dist: myst-parser[linkify]; extra == 'docs'
Requires-Dist: sphinx>=7.0.0; extra == 'docs'
Provides-Extra: notebooks
Requires-Dist: altair; extra == 'notebooks'
Requires-Dist: jupyterlab; extra == 'notebooks'
Requires-Dist: pandas; extra == 'notebooks'
Requires-Dist: treon; extra == 'notebooks'
Provides-Extra: test
Requires-Dist: pytest-cov; extra == 'test'
Requires-Dist: pytest-ordering; extra == 'test'
Requires-Dist: pytest>=7.2; extra == 'test'
